rcv/__init__.py
rcv/ballot.py
rcv/candidate.py
rcv/processing.py
rcv/sampling.py
rcv/schedule.py
rcv/stv.py
rcv/values_dict.py
rcv/weighted_set.py
rcv-0.1.2.dist-info/LICENSE
rcv-0.1.2.dist-info/METADATA
rcv-0.1.2.dist-info/WHEEL
rcv-0.1.2.dist-info/top_level.txt
rcv-0.1.2.dist-info/RECORD
