Metadata-Version: 2.1
Name: rcv
Version: 0.1.2
Summary: Tabulate ballots from ranked-choice elections
Home-page: https://github.com/gerrymandr/rcv
Author: Max Hully
Author-email: max@mggg.org
License: UNKNOWN
Platform: UNKNOWN
Classifier: Programming Language :: Python :: 3.6
Classifier: Programming Language :: Python :: 3.7
Classifier: Operating System :: OS Independent
Classifier: License :: OSI Approved :: BSD License
Provides-Extra: sample
Requires-Dist: numpy (>=1.7) ; extra == 'sample'
Provides-Extra: test
Requires-Dist: pandas ; extra == 'test'
Requires-Dist: pytest ; extra == 'test'
Requires-Dist: pytest-cov ; extra == 'test'
